osw_incline/__init__.py
osw_incline/dem_processor.py
osw_incline/logger.py
osw_incline/osm_graph.py
osw_incline/version.py
utils/__init__.py
osw_incline-0.0.4.dist-info/LICENSE
osw_incline-0.0.4.dist-info/METADATA
osw_incline-0.0.4.dist-info/WHEEL
osw_incline-0.0.4.dist-info/top_level.txt
osw_incline-0.0.4.dist-info/RECORD
