Metadata-Version: 2.1
Name: osw-incline
Version: 0.0.4
Summary: Python package to calculates the Incline of given edges 
Home-page: https://github.com/TaskarCenterAtUW/TDEI-python-lib-osw-inclination
Author: Sujata Misra
Author-email: sujatam@gaussiansolutions.com
Project-URL: Documentation, https://github.com/TaskarCenterAtUW/TDEI-python-lib-osw-inclination/blob/main/README.md
Project-URL: GitHub, https://github.com/TaskarCenterAtUW/TDEI-python-lib-osw-inclination
Project-URL: Changelog, https://github.com/TaskarCenterAtUW/TDEI-python-lib-osw-inclination/blob/main/CHANGELOG.md
Classifier: Programming Language :: Python :: 3
Classifier: License :: OSI Approved :: MIT License
Classifier: Operating System :: OS Independent
Requires-Python: >=3.10
License-File: LICENSE
Requires-Dist: pyproj
Requires-Dist: networkx
Requires-Dist: shapely
Requires-Dist: rasterio
Requires-Dist: numpy
Requires-Dist: scipy
